openbb_econdb/__init__.py
openbb_econdb/models/__init__.py
openbb_econdb/models/available_indicators.py
openbb_econdb/models/country_profile.py
openbb_econdb/models/economic_indicators.py
openbb_econdb/models/export_destinations.py
openbb_econdb/models/gdp_nominal.py
openbb_econdb/models/gdp_real.py
openbb_econdb/models/port_volume.py
openbb_econdb/models/yield_curve.py
openbb_econdb/utils/__init__.py
openbb_econdb/utils/helpers.py
openbb_econdb/utils/indicator_countries.json
openbb_econdb/utils/indicators_descriptions.json
openbb_econdb/utils/main_indicators.py
openbb_econdb/utils/multipliers.json
openbb_econdb/utils/scales.json
openbb_econdb/utils/symbol_to_indicator.json
openbb_econdb/utils/units.json
openbb_econdb/utils/yield_curves.py
openbb_econdb-1.3.1.dist-info/METADATA
openbb_econdb-1.3.1.dist-info/WHEEL
openbb_econdb-1.3.1.dist-info/entry_points.txt
openbb_econdb-1.3.1.dist-info/RECORD
